Metadata-Version: 2.4
Name: django-session-security-continued
Version: 3.0.0a2
Summary: Client and server-side session timeout enforcement with warnings for Django 4.2+.
Author: Matt Bosworth (https://github.com/mattbo), Fabio Caritas Barrionuevo da Luz (https://github.com/luzfcb), Pēteris Caune (https://github.com/cuu508), John David Giese (https://github.com/johndgiese), Jose Antonio Martin Prieto (https://github.com/jantoniomartin), Richard Moorhead (https://github.com/autodidacticon), Jean-Michel Nirgal Vourgère (https://github.com/nirgal), Michał Pasternak (https://github.com/mpasternak), James Pic (https://github.com/jpic), Matthew Schettler (https://githu
Maintainer-email: Arrai Innovations <support@arrai.com>
Project-URL: repository, https://github.com/arrai-innovations/django-session-security-continued
Classifier: Development Status :: 5 - Production/Stable
Classifier: Environment :: Web Environment
Classifier: Framework :: Django
Classifier: Framework :: Django :: 4.2
Classifier: Framework :: Django :: 5.0
Classifier: Framework :: Django :: 5.1
Classifier: Framework :: Django :: 5.2
Classifier: Intended Audience :: Developers
Classifier: Operating System :: OS Independent
Classifier: Programming Language :: Python
Classifier: Programming Language :: Python :: 3
Classifier: Programming Language :: Python :: 3.9
Classifier: Programming Language :: Python :: 3.10
Classifier: Programming Language :: Python :: 3.11
Classifier: Programming Language :: Python :: 3.12
Classifier: Topic :: Internet :: WWW/HTTP
Classifier: Topic :: Software Development :: Libraries :: Python Modules
Requires-Python: >=3.9
License-File: LICENSE
Requires-Dist: django<5.3,>=4.2
Dynamic: license-file
